djcloudbridge/__init__.py
djcloudbridge/admin.py
djcloudbridge/apps.py
djcloudbridge/domain_model.py
djcloudbridge/drf_helpers.py
djcloudbridge/drf_routers.py
djcloudbridge/forms.py
djcloudbridge/models.py
djcloudbridge/serializers.py
djcloudbridge/urls.py
djcloudbridge/util.py
djcloudbridge/view_helpers.py
djcloudbridge/views.py
djcloudbridge/migrations/0001_initial.py
djcloudbridge/migrations/0002_flatten_aws_cloud_model.py
djcloudbridge/migrations/0003_move_azure_cloud_fields_to_creds.py
djcloudbridge/migrations/__init__.py
djcloudbridge/profile/__init__.py
djcloudbridge/profile/urls.py
djcloudbridge/templates/djcloudbridge/base.html
djcloudbridge-0.3.1.dist-info/DESCRIPTION.rst
djcloudbridge-0.3.1.dist-info/METADATA
djcloudbridge-0.3.1.dist-info/RECORD
djcloudbridge-0.3.1.dist-info/WHEEL
djcloudbridge-0.3.1.dist-info/metadata.json
djcloudbridge-0.3.1.dist-info/top_level.txt
