Metadata-Version: 2.0
Name: djcloudbridge
Version: 0.3.1
Summary: A ReSTful web api backed by cloudbridge for interacting with cloud providers
Home-page: https://github.com/cloudve/djcloudbridge
Author: Galaxy and GVL Projects
Author-email: help@CloudVE.org
License: MIT
Keywords: djcloudbridge
Platform: UNKNOWN
Classifier: Development Status :: 4 - Beta
Classifier: Framework :: Django
Classifier: Framework :: Django :: 1.11
Classifier: Intended Audience :: Developers
Classifier: License :: OSI Approved :: BSD License
Classifier: Natural Language :: English
Classifier: Programming Language :: Python :: 3.6
Requires-Dist: django-model-utils (>=3.0)
Requires-Dist: djangorestframework (>=3.0.0)
Requires-Dist: drf-nested-routers
Requires-Dist: django-rest-auth
Requires-Dist: django-fernet-fields
Requires-Dist: cloudbridge
Provides-Extra: dev
Requires-Dist: sphinx (>=1.3.1); extra == 'dev'
Requires-Dist: bumpversion (>=0.5.3); extra == 'dev'
Requires-Dist: tox (>=2.9.1); extra == 'dev'
Requires-Dist: coverage (>=4.4.1); extra == 'dev'
Requires-Dist: flake8 (>=3.4.1); extra == 'dev'
Requires-Dist: flake8-import-order (>=0.13); extra == 'dev'
Requires-Dist: django-model-utils (>=3.0); extra == 'dev'
Requires-Dist: djangorestframework (>=3.0.0); extra == 'dev'
Requires-Dist: drf-nested-routers; extra == 'dev'
Requires-Dist: django-rest-auth; extra == 'dev'
Requires-Dist: django-fernet-fields; extra == 'dev'
Requires-Dist: cloudbridge; extra == 'dev'
Provides-Extra: test
Requires-Dist: tox (>=2.9.1); extra == 'test'
Requires-Dist: coverage (>=4.4.1); extra == 'test'
Requires-Dist: flake8 (>=3.4.1); extra == 'test'
Requires-Dist: flake8-import-order (>=0.13); extra == 'test'
Requires-Dist: django-model-utils (>=3.0); extra == 'test'
Requires-Dist: djangorestframework (>=3.0.0); extra == 'test'
Requires-Dist: drf-nested-routers; extra == 'test'
Requires-Dist: django-rest-auth; extra == 'test'
Requires-Dist: django-fernet-fields; extra == 'test'
Requires-Dist: cloudbridge; extra == 'test'
